image2sketch/__init__.py
image2sketch/convert_image.py
image2sketch-1.0.0.dist-info/LICENSE
image2sketch-1.0.0.dist-info/METADATA
image2sketch-1.0.0.dist-info/WHEEL
image2sketch-1.0.0.dist-info/top_level.txt
image2sketch-1.0.0.dist-info/RECORD
