Metadata-Version: 2.1
Name: image2sketch
Version: 1.0.0
Summary: Convert a image to a pencil sketch picture.
Author-email: wyjstudio <wyjstudio@126.com>
Project-URL: Homepage, https://github.com/wyjstudio/PythonShare
Project-URL: Bug Tracker, https://github.com/wyjstudio/PythonShare/issues
Classifier: Programming Language :: Python :: 3
Classifier: License :: OSI Approved :: MIT License
Classifier: Operating System :: OS Independent
Requires-Python: >=3.7
License-File: LICENSE
